ro_utils/__init__.py
ro_utils/debug.py
ro_utils/decorator.py
ro_utils/response.py
ro_utils/cookie/__init__.py
ro_utils/cookie/base.py
ro_utils/cookie/json_cookie.py
ro_utils/cookie/text_cookie.py
ro_utils-0.4.0.dist-info/METADATA
ro_utils-0.4.0.dist-info/WHEEL
ro_utils-0.4.0.dist-info/top_level.txt
ro_utils-0.4.0.dist-info/RECORD
