Metadata-Version: 2.1
Name: ro-utils
Version: 0.4.0
Summary: utils for daily usage
Author-email: rogerogers <rogers@rogerogers.com>
Project-URL: Homepage, https://github.com/rogerogers/python-ro-utils
Project-URL: Repository, https://github.com/rogerogers/python-ro-utils
Project-URL: Issues, https://github.com/rogerogers/python-ro-utils/issues
Requires-Python: >=3.10
